llama_index/readers/oxylabs/__init__.py
llama_index/readers/oxylabs/amazon_bestsellers.py
llama_index/readers/oxylabs/amazon_pricing.py
llama_index/readers/oxylabs/amazon_product.py
llama_index/readers/oxylabs/amazon_reviews.py
llama_index/readers/oxylabs/amazon_search.py
llama_index/readers/oxylabs/amazon_sellers.py
llama_index/readers/oxylabs/base.py
llama_index/readers/oxylabs/google_ads.py
llama_index/readers/oxylabs/google_base.py
llama_index/readers/oxylabs/google_search.py
llama_index/readers/oxylabs/utils.py
llama_index/readers/oxylabs/youtube_transcripts.py
llama_index_readers_oxylabs-0.1.2.dist-info/METADATA
llama_index_readers_oxylabs-0.1.2.dist-info/WHEEL
llama_index_readers_oxylabs-0.1.2.dist-info/licenses/LICENSE
llama_index_readers_oxylabs-0.1.2.dist-info/RECORD
