Metadata-Version: 2.4
Name: llama-index-readers-oxylabs
Version: 0.1.2
Summary: llama-index readers oxylabs integration
Author-email: Rostyslav Borovyk <rostyslav.borovyk@oxylabs.io>
License-Expression: MIT
License-File: LICENSE
Requires-Python: <4.0,>=3.9
Requires-Dist: httpx>=0.28.1
Requires-Dist: llama-index-core>=0.12.34.post1
Requires-Dist: lxml-html-clean>=0.4.2
Requires-Dist: lxml>=5.4.0
Requires-Dist: markdownify>=1.1.0
Requires-Dist: oxylabs>=2.0.0
